ban/__init__.py
ban/cli.py
ban-0.1.0.dist-info/LICENSE
ban-0.1.0.dist-info/METADATA
ban-0.1.0.dist-info/WHEEL
ban-0.1.0.dist-info/entry_points.txt
ban-0.1.0.dist-info/top_level.txt
ban-0.1.0.dist-info/RECORD
