Metadata-Version: 2.1
Name: ban
Version: 0.1.0
Summary: python 开源命令行办公工具。
Home-page: https://github.com/kenblikylee/ban.git
Author: kenblikylee
Author-email: kenblikylee@126.com
License: MIT
Platform: UNKNOWN
Classifier: Programming Language :: Python :: 3
Classifier: License :: OSI Approved :: MIT License
Classifier: Operating System :: OS Independent
Requires-Python: >=3.6
